pybtexnbib/__init__.py
pybtexnbib/data/types.csv
pybtexnbib/parsers.py
pybtexnbib-0.1.2.dist-info/entry_points.txt
pybtexnbib-0.1.2.dist-info/LICENSE
pybtexnbib-0.1.2.dist-info/WHEEL
pybtexnbib-0.1.2.dist-info/METADATA
pybtexnbib-0.1.2.dist-info/RECORD
