Metadata-Version: 2.1
Name: pybtexnbib
Version: 0.1.2
Summary: A pybtex plugin for NBIB/Medline/PubMed files
Home-page: https://github.com/rbturnbull/pybtexnbib
License: Apache-2.0
Author: Robert Turnbull
Author-email: robert.turnbull@unimelb.edu.au
Requires-Python: >=3.7.1,<4.0.0
Classifier: License :: OSI Approved :: Apache Software License
Classifier: Programming Language :: Python :: 3
Classifier: Programming Language :: Python :: 3.10
Classifier: Programming Language :: Python :: 3.8
Classifier: Programming Language :: Python :: 3.9
Requires-Dist: pybtex (>=0.24.0,<0.25.0)
Requires-Dist: pybtexris (>=0.1.2,<0.2.0)
Project-URL: Repository, https://github.com/rbturnbull/pybtexnbib
